BetterString/BetterString.py
BetterString/BetterString.pyi
BetterString/Color.py
BetterString/Color.pyi
BetterString/Exceptions.py
BetterString/Exceptions.pyi
BetterString/__init__.py
BetterString/__init__.pyi
BetterString/__main__.py
BetterString/__main__.pyi
BetterString/constants.py
BetterString/constants.pyi
BetterString-2.17.3.dist-info/LICENSE
BetterString-2.17.3.dist-info/METADATA
BetterString-2.17.3.dist-info/WHEEL
BetterString-2.17.3.dist-info/top_level.txt
BetterString-2.17.3.dist-info/RECORD
