Metadata-Version: 2.1
Name: BetterString
Version: 2.17.3
Summary: Like a normal string but with more functionality
Home-page: UNKNOWN
Author: DerSchinken
License: UNKNOWN
Project-URL: Homepage, http://index12.bplaced.net/
Project-URL: Github, https://github.com/DerSchinken/BetterString
Platform: UNKNOWN
Classifier: Intended Audience :: Developers
Classifier: Operating System :: OS Independent
Classifier: Programming Language :: Python :: 3.6
Classifier: Programming Language :: Python :: 3.7
Classifier: Programming Language :: Python :: 3.8
Classifier: Programming Language :: Python :: 3.9
Classifier: Programming Language :: Python :: 3.10
Requires-Python: >=3.6
Requires-Dist: colorama (~=0.4.4)
